<?xml version="1.0" encoding="UTF-8"?>
<schemalist gettext-domain="mate-applets">
  <schema id="org.mate.panel.applet.multiload">
    <key type="b" name="view-cpuload">
      <default>true</default>
      <summary>Enable CPU load graph</summary>
    </key>
    <key type="b" name="view-memload">
      <default>false</default>
      <summary>Enable memory load graph</summary>
    </key>
    <key type="b" name="view-netload">
      <default>false</default>
      <summary>Enable network load graph</summary>
    </key>
    <key type="b" name="view-swapload">
      <default>false</default>
      <summary>Enable swap load graph</summary>
    </key>
    <key type="b" name="view-loadavg">
      <default>false</default>
      <summary>Enable load average graph</summary>
    </key>
    <key type="b" name="view-diskload">
      <default>false</default>
      <summary>Enable disk load graph</summary>
    </key>
    <key type="i" name="speed">
      <default>500</default>
      <summary>Applet refresh rate in milliseconds</summary>
    </key>
    <key type="i" name="size">
      <default>40</default>
      <summary>Graph size</summary>
      <description>For horizontal panels, the width of the graphs in pixels.  For vertical panels, this is the height of the graphs.</description>
    </key>
    <key type="s" name="cpuload-color0">
      <default>'#0072b3'</default>
      <summary>Graph color for user-related CPU activity</summary>
    </key>
    <key type="s" name="cpuload-color1">
      <default>'#0092e6'</default>
      <summary>Graph color for system-related CPU activity</summary>
    </key>
    <key type="s" name="cpuload-color2">
      <default>'#00a3ff'</default>
      <summary>Graph color for nice-related CPU activity</summary>
    </key>
    <key type="s" name="cpuload-color3">
      <default>'#002f3d'</default>
      <summary>Graph color for iowait related CPU activity</summary>
    </key>
    <key type="s" name="cpuload-color4">
      <default>'#000000'</default>
      <summary>CPU graph background color</summary>
    </key>
    <key type="s" name="memload-color0">
      <default>'#00b35b'</default>
      <summary>Graph color for user-related memory usage</summary>
    </key>
    <key type="s" name="memload-color1">
      <default>'#00e675'</default>
      <summary>Graph color for shared memory</summary>
    </key>
    <key type="s" name="memload-color2">
      <default>'#00ff82'</default>
      <summary>Graph color for buffer memory</summary>
    </key>
    <key type="s" name="memload-color3">
      <default>'#AAF5D0'</default>
      <summary>Graph color for cached memory</summary>
    </key>
    <key type="s" name="memload-color4">
      <default>'#000000'</default>
      <summary>Memory graph background color</summary>
    </key>
    <key type="s" name="netload2-color0">
      <default>'#fce94f'</default>
      <summary>Graph color for input network activity</summary>
    </key>
    <key type="s" name="netload2-color1">
      <default>'#edd400'</default>
      <summary>Graph color for output network activity</summary>
    </key>
    <key type="s" name="netload2-color2">
      <default>'#c4a000'</default>
      <summary>Graph color for loopback network usage</summary>
    </key>
    <key type="s" name="netload2-color3">
      <default>'#000000'</default>
      <summary>Network graph background color</summary>
    </key>
    <key type="s" name="swapload-color0">
      <default>'#8b00c3'</default>
      <summary>Graph color for user-related swap usage</summary>
    </key>
    <key type="s" name="swapload-color1">
      <default>'#000000'</default>
      <summary>Swap graph background color</summary>
    </key>
    <key type="s" name="loadavg-color0">
      <default>'#d50000'</default>
      <summary>Graph color for load average</summary>
    </key>
    <key type="s" name="loadavg-color1">
      <default>'#000000'</default>
      <summary>Load graph background color</summary>
    </key>
    <key type="s" name="diskload-color0">
      <default>'#C65000'</default>
      <summary>Graph color for disk read</summary>
    </key>
    <key type="s" name="diskload-color1">
      <default>'#FF6700'</default>
      <summary>Graph color for disk write</summary>
    </key>
    <key type="s" name="diskload-color2">
      <default>'#000000'</default>
      <summary>Background color for disk load graph</summary>
    </key>
    <key type="s" name="system-monitor">
      <default>'mate-system-monitor.desktop'</default>
      <summary>The desktop description file to execute as the system monitor</summary>
    </key>
  </schema>
</schemalist>